[
  {
    "trail_amount": null,
    "product_id": 92703,
    "user_id": 21672861,
    "bracket_stop_loss_price": null,
    "stop_order_type": null,
    "bracket_take_profit_limit_price": null,
    "stop_price": null,
    "stop_trigger_method": null,
    "state": "open",
    "bracket_order": null,
    "id": 936644904,
    "bracket_stop_loss_limit_price": null,
    "client_order_id": null,
    "quote_size": null,
    "product_symbol": "P-ETH-5000-311025",
    "commission": "0",
    "bracket_trail_amount": null,
    "unfilled_size": 35,
    "mmp": "disabled",
    "cancellation_reason": null,
    "order_type": "limit_order",
    "average_fill_price": "590",
    "updated_at": "2025-09-18T00:56:19.308021Z",
    "size": 36,
    "time_in_force": "gtc",
    "product": {
      "contract_type": "put_options",
      "contract_unit_currency": "ETH",
      "contract_value": "0.01",
      "id": 92703,
      "notional_type": "vanilla",
      "quoting_asset": {
        "minimum_precision": 2,
        "precision": 8,
        "symbol": "USD"
      },
      "settling_asset": {
        "minimum_precision": 2,
        "precision": 8,
        "symbol": "USD"
      },
      "spot_index": {
        "symbol": ".DEETHUSD"
      },
      "symbol": "P-ETH-5000-311025",
      "tick_size": "0.01",
      "underlying_asset": {
        "minimum_precision": 4,
        "precision": 18,
        "symbol": "ETH"
      }
    },
    "side": "sell",
    "paid_commission": "0.00813448",
    "reduce_only": true,
    "bracket_take_profit_price": null,
    "limit_price": 599.7,
    "meta_data": {
      "avg_exit_price": "590",
      "cashflow": "5.9",
      "entry_price": "524.0056756756756756756756757",
      "exit_price_with_size": [
        {
          "price": "590.00000000",
          "size": "1"
        }
      ],
      "ip": "2409:40e5:9:d71f:8000::",
      "otc": false,
      "pnl": "0.65994324",
      "roe": "0.3498388952186234142639607609",
      "source": "mobile_app_android",
      "user_updated_at": "2025-09-18T00:56:19.307Z"
    },
    "close_on_trigger": "false",
    "created_at": "2025-09-18T00:49:06.370541Z"
  },
  {
    "trail_amount": null,
    "product_id": 92535,
    "user_id": 21672861,
    "bracket_stop_loss_price": null,
    "stop_order_type": null,
    "bracket_take_profit_limit_price": null,
    "stop_price": null,
    "stop_trigger_method": null,
    "state": "open",
    "bracket_order": null,
    "id": 936639390,
    "bracket_stop_loss_limit_price": null,
    "client_order_id": null,
    "quote_size": null,
    "product_symbol": "P-ETH-4500-311025",
    "commission": "0",
    "bracket_trail_amount": null,
    "unfilled_size": 75,
    "mmp": "disabled",
    "cancellation_reason": null,
    "order_type": "limit_order",
    "average_fill_price": null,
    "updated_at": "2025-09-18T00:55:38.314770Z",
    "size": 75,
    "time_in_force": "gtc",
    "product": {
      "contract_type": "put_options",
      "contract_unit_currency": "ETH",
      "contract_value": "0.01",
      "id": 92535,
      "notional_type": "vanilla",
      "quoting_asset": {
        "minimum_precision": 2,
        "precision": 8,
        "symbol": "USD"
      },
      "settling_asset": {
        "minimum_precision": 2,
        "precision": 8,
        "symbol": "USD"
      },
      "spot_index": {
        "symbol": ".DEETHUSD"
      },
      "symbol": "P-ETH-4500-311025",
      "tick_size": "0.01",
      "underlying_asset": {
        "minimum_precision": 4,
        "precision": 18,
        "symbol": "ETH"
      }
    },
    "side": "sell",
    "paid_commission": "0",
    "reduce_only": true,
    "bracket_take_profit_price": null,
    "limit_price": "293",
    "meta_data": {
      "ip": "2409:40e5:9:d71f:8000::",
      "otc": false,
      "source": "mobile_app_android",
      "user_updated_at": "2025-09-18T00:55:38.314Z"
    },
    "close_on_trigger": "false",
    "created_at": "2025-09-18T00:43:09.515798Z"
  },
  {
    "trail_amount": null,
    "product_id": 92535,
    "user_id": 21672861,
    "bracket_stop_loss_price": null,
    "stop_order_type": null,
    "bracket_take_profit_limit_price": null,
    "stop_price": null,
    "stop_trigger_method": null,
    "state": "open",
    "bracket_order": null,
    "id": 936623814,
    "bracket_stop_loss_limit_price": null,
    "client_order_id": null,
    "quote_size": null,
    "product_symbol": "P-ETH-4500-311025",
    "commission": "0",
    "bracket_trail_amount": null,
    "unfilled_size": 20,
    "mmp": "disabled",
    "cancellation_reason": null,
    "order_type": "limit_order",
    "average_fill_price": null,
    "updated_at": "2025-09-18T00:42:27.666857Z",
    "size": 20,
    "time_in_force": "gtc",
    "product": {
      "contract_type": "put_options",
      "contract_unit_currency": "ETH",
      "contract_value": "0.01",
      "id": 92535,
      "notional_type": "vanilla",
      "quoting_asset": {
        "minimum_precision": 2,
        "precision": 8,
        "symbol": "USD"
      },
      "settling_asset": {
        "minimum_precision": 2,
        "precision": 8,
        "symbol": "USD"
      },
      "spot_index": {
        "symbol": ".DEETHUSD"
      },
      "symbol": "P-ETH-4500-311025",
      "tick_size": "0.01",
      "underlying_asset": {
        "minimum_precision": 4,
        "precision": 18,
        "symbol": "ETH"
      }
    },
    "side": "buy",
    "paid_commission": "0",
    "reduce_only": false,
    "bracket_take_profit_price": null,
    "limit_price": "75.1",
    "meta_data": {
      "ip": "2409:40e5:9:d71f:8000::",
      "otc": false,
      "source": "mobile_app_android",
      "user_updated_at": "2025-09-18T00:42:27.666Z"
    },
    "close_on_trigger": "false",
    "created_at": "2025-09-18T00:28:57.687211Z"
  },
  {
    "trail_amount": null,
    "product_id": 92541,
    "user_id": 21672861,
    "bracket_stop_loss_price": null,
    "stop_order_type": null,
    "bracket_take_profit_limit_price": null,
    "stop_price": null,
    "stop_trigger_method": null,
    "state": "open",
    "bracket_order": null,
    "id": 936598785,
    "bracket_stop_loss_limit_price": null,
    "client_order_id": null,
    "quote_size": null,
    "product_symbol": "C-ETH-4500-311025",
    "commission": "0",
    "bracket_trail_amount": null,
    "unfilled_size": 20,
    "mmp": "disabled",
    "cancellation_reason": null,
    "order_type": "limit_order",
    "average_fill_price": null,
    "updated_at": "2025-09-17T23:59:35.377452Z",
    "size": 20,
    "time_in_force": "gtc",
    "product": {
      "contract_type": "call_options",
      "contract_unit_currency": "ETH",
      "contract_value": "0.01",
      "id": 92541,
      "notional_type": "vanilla",
      "quoting_asset": {
        "minimum_precision": 2,
        "precision": 8,
        "symbol": "USD"
      },
      "settling_asset": {
        "minimum_precision": 2,
        "precision": 8,
        "symbol": "USD"
      },
      "spot_index": {
        "symbol": ".DEETHUSD"
      },
      "symbol": "C-ETH-4500-311025",
      "tick_size": "0.01",
      "underlying_asset": {
        "minimum_precision": 4,
        "precision": 18,
        "symbol": "ETH"
      }
    },
    "side": "buy",
    "paid_commission": "0",
    "reduce_only": false,
    "bracket_take_profit_price": null,
    "limit_price": "252.1",
    "meta_data": {
      "ip": "2409:40e5:9:d71f:8000::",
      "otc": false,
      "source": "mobile_app_android"
    },
    "close_on_trigger": "false",
    "created_at": "2025-09-17T23:59:35.377452Z"
  },
  {
    "trail_amount": null,
    "product_id": 92703,
    "user_id": 21672861,
    "bracket_stop_loss_price": null,
    "stop_order_type": null,
    "bracket_take_profit_limit_price": null,
    "stop_price": null,
    "stop_trigger_method": null,
    "state": "open",
    "bracket_order": null,
    "id": 936598132,
    "bracket_stop_loss_limit_price": null,
    "client_order_id": null,
    "quote_size": null,
    "product_symbol": "P-ETH-5000-311025",
    "commission": "0",
    "bracket_trail_amount": null,
    "unfilled_size": 5,
    "mmp": "disabled",
    "cancellation_reason": null,
    "order_type": "limit_order",
    "average_fill_price": null,
    "updated_at": "2025-09-17T23:58:27.708204Z",
    "size": 5,
    "time_in_force": "gtc",
    "product": {
      "contract_type": "put_options",
      "contract_unit_currency": "ETH",
      "contract_value": "0.01",
      "id": 92703,
      "notional_type": "vanilla",
      "quoting_asset": {
        "minimum_precision": 2,
        "precision": 8,
        "symbol": "USD"
      },
      "settling_asset": {
        "minimum_precision": 2,
        "precision": 8,
        "symbol": "USD"
      },
      "spot_index": {
        "symbol": ".DEETHUSD"
      },
      "symbol": "P-ETH-5000-311025",
      "tick_size": "0.01",
      "underlying_asset": {
        "minimum_precision": 4,
        "precision": 18,
        "symbol": "ETH"
      }
    },
    "side": "buy",
    "paid_commission": "0",
    "reduce_only": false,
    "bracket_take_profit_price": null,
    "limit_price": "467",
    "meta_data": {
      "ip": "2409:40e5:9:d71f:8000::",
      "otc": false,
      "source": "mobile_app_android"
    },
    "close_on_trigger": "false",
    "created_at": "2025-09-17T23:58:27.708204Z"
  },
  {
    "trail_amount": null,
    "product_id": 92703,
    "user_id": 21672861,
    "bracket_stop_loss_price": null,
    "stop_order_type": null,
    "bracket_take_profit_limit_price": null,
    "stop_price": null,
    "stop_trigger_method": null,
    "state": "open",
    "bracket_order": null,
    "id": 936155798,
    "bracket_stop_loss_limit_price": null,
    "client_order_id": null,
    "quote_size": null,
    "product_symbol": "P-ETH-5000-311025",
    "commission": "0",
    "bracket_trail_amount": null,
    "unfilled_size": 10,
    "mmp": "disabled",
    "cancellation_reason": null,
    "order_type": "limit_order",
    "average_fill_price": null,
    "updated_at": "2025-09-17T20:37:03.901821Z",
    "size": 10,
    "time_in_force": "gtc",
    "product": {
      "contract_type": "put_options",
      "contract_unit_currency": "ETH",
      "contract_value": "0.01",
      "id": 92703,
      "notional_type": "vanilla",
      "quoting_asset": {
        "minimum_precision": 2,
        "precision": 8,
        "symbol": "USD"
      },
      "settling_asset": {
        "minimum_precision": 2,
        "precision": 8,
        "symbol": "USD"
      },
      "spot_index": {
        "symbol": ".DEETHUSD"
      },
      "symbol": "P-ETH-5000-311025",
      "tick_size": "0.01",
      "underlying_asset": {
        "minimum_precision": 4,
        "precision": 18,
        "symbol": "ETH"
      }
    },
    "side": "buy",
    "paid_commission": "0",
    "reduce_only": false,
    "bracket_take_profit_price": null,
    "limit_price": "362.5",
    "meta_data": {
      "ip": "2409:40e5:b6:40e8:8000::",
      "otc": false,
      "source": "mobile_app_android",
      "user_updated_at": "2025-09-17T20:37:03.901Z"
    },
    "close_on_trigger": "false",
    "created_at": "2025-09-17T18:33:56.070159Z"
  },
  {
    "trail_amount": null,
    "product_id": 92761,
    "user_id": 21672861,
    "bracket_stop_loss_price": null,
    "stop_order_type": null,
    "bracket_take_profit_limit_price": null,
    "stop_price": null,
    "stop_trigger_method": null,
    "state": "open",
    "bracket_order": null,
    "id": 935871630,
    "bracket_stop_loss_limit_price": null,
    "client_order_id": null,
    "quote_size": null,
    "product_symbol": "P-ETH-3500-311025",
    "commission": "0",
    "bracket_trail_amount": null,
    "unfilled_size": 10,
    "mmp": "disabled",
    "cancellation_reason": null,
    "order_type": "limit_order",
    "average_fill_price": null,
    "updated_at": "2025-09-18T00:00:22.199639Z",
    "size": 10,
    "time_in_force": "gtc",
    "product": {
      "contract_type": "put_options",
      "contract_unit_currency": "ETH",
      "contract_value": "0.01",
      "id": 92761,
      "notional_type": "vanilla",
      "quoting_asset": {
        "minimum_precision": 2,
        "precision": 8,
        "symbol": "USD"
      },
      "settling_asset": {
        "minimum_precision": 2,
        "precision": 8,
        "symbol": "USD"
      },
      "spot_index": {
        "symbol": ".DEETHUSD"
      },
      "symbol": "P-ETH-3500-311025",
      "tick_size": "0.01",
      "underlying_asset": {
        "minimum_precision": 4,
        "precision": 18,
        "symbol": "ETH"
      }
    },
    "side": "buy",
    "paid_commission": "0",
    "reduce_only": false,
    "bracket_take_profit_price": null,
    "limit_price": "17.11",
    "meta_data": {
      "ip": "2409:40e4:2c:dec4:8000::",
      "otc": false,
      "source": "mobile_app_android",
      "user_updated_at": "2025-09-18T00:00:22.199Z"
    },
    "close_on_trigger": "false",
    "created_at": "2025-09-17T17:30:53.635376Z"
  },
  {
    "trail_amount": null,
    "product_id": 92541,
    "user_id": 21672861,
    "bracket_stop_loss_price": null,
    "stop_order_type": null,
    "bracket_take_profit_limit_price": null,
    "stop_price": null,
    "stop_trigger_method": null,
    "state": "open",
    "bracket_order": null,
    "id": 935525795,
    "bracket_stop_loss_limit_price": null,
    "client_order_id": null,
    "quote_size": null,
    "product_symbol": "C-ETH-4500-311025",
    "commission": "0",
    "bracket_trail_amount": null,
    "unfilled_size": 50,
    "mmp": "disabled",
    "cancellation_reason": null,
    "order_type": "limit_order",
    "average_fill_price": null,
    "updated_at": "2025-09-17T13:40:51.974895Z",
    "size": 50,
    "time_in_force": "gtc",
    "product": {
      "contract_type": "call_options",
      "contract_unit_currency": "ETH",
      "contract_value": "0.01",
      "id": 92541,
      "notional_type": "vanilla",
      "quoting_asset": {
        "minimum_precision": 2,
        "precision": 8,
        "symbol": "USD"
      },
      "settling_asset": {
        "minimum_precision": 2,
        "precision": 8,
        "symbol": "USD"
      },
      "spot_index": {
        "symbol": ".DEETHUSD"
      },
      "symbol": "C-ETH-4500-311025",
      "tick_size": "0.01",
      "underlying_asset": {
        "minimum_precision": 4,
        "precision": 18,
        "symbol": "ETH"
      }
    },
    "side": "buy",
    "paid_commission": "0",
    "reduce_only": false,
    "bracket_take_profit_price": null,
    "limit_price": "155",
    "meta_data": {
      "ip": "2409:40e4:43:ab65:8000::",
      "otc": false,
      "source": "mobile_app_android"
    },
    "close_on_trigger": "false",
    "created_at": "2025-09-17T13:40:51.974895Z"
  }
]