[
  {
    "stop_order_type": null,
    "reduce_only": false,
    "average_fill_price": null,
    "user_id": 21672861,
    "side": "sell",
    "trail_amount": null,
    "quote_size": null,
    "state": "open",
    "id": 1177622584,
    "stop_price": null,
    "margin_mode": "portfolio",
    "time_in_force": "gtc",
    "client_order_id": null,
    "meta_data": {
      "ip": "2409:40e5:be:76c9:8000::",
      "otc": false,
      "source": "mobile_app_android"
    },
    "product_id": 122137,
    "product_symbol": "P-BTC-69200-150226",
    "stop_trigger_method": null,
    "order_type": "limit_order",
    "unfilled_size": 500,
    "bracket_take_profit_limit_price": null,
    "product": {
      "contract_type": "put_options",
      "contract_unit_currency": "BTC",
      "contract_value": "0.001",
      "id": 122137,
      "notional_type": "vanilla",
      "quoting_asset": {
        "minimum_precision": 2,
        "precision": 8,
        "symbol": "USD"
      },
      "settling_asset": {
        "minimum_precision": 2,
        "precision": 8,
        "symbol": "USD"
      },
      "spot_index": {
        "symbol": ".DEXBTUSD"
      },
      "symbol": "P-BTC-69200-150226",
      "tick_size": "0.1",
      "underlying_asset": {
        "minimum_precision": 4,
        "precision": 8,
        "symbol": "BTC"
      }
    },
    "limit_price": "70",
    "bracket_trail_amount": null,
    "commission": "0",
    "bracket_order": null,
    "created_at": "2026-02-15T03:55:20.033180Z",
    "size": 500,
    "cancellation_reason": null,
    "bracket_stop_loss_price": null,
    "bracket_take_profit_price": null,
    "mmp": "disabled",
    "updated_at": "2026-02-15T03:55:20.033180Z",
    "paid_commission": "0",
    "bracket_stop_loss_limit_price": null
  },
  {
    "stop_order_type": null,
    "reduce_only": false,
    "average_fill_price": "12",
    "user_id": 21672861,
    "side": "buy",
    "trail_amount": null,
    "quote_size": null,
    "state": "open",
    "id": 1177621427,
    "stop_price": null,
    "margin_mode": "portfolio",
    "time_in_force": "gtc",
    "client_order_id": null,
    "meta_data": {
      "cashflow": "-4.212",
      "ip": "2409:40e5:be:76c9:8000::",
      "otc": false,
      "pnl": "-0",
      "source": "mobile_app_android",
      "user_updated_at": "2026-02-15T03:56:08.787Z"
    },
    "product_id": 122098,
    "product_symbol": "P-BTC-68800-150226",
    "stop_trigger_method": null,
    "order_type": "limit_order",
    "unfilled_size": 449,
    "bracket_take_profit_limit_price": null,
    "product": {
      "contract_type": "put_options",
      "contract_unit_currency": "BTC",
      "contract_value": "0.001",
      "id": 122098,
      "notional_type": "vanilla",
      "quoting_asset": {
        "minimum_precision": 2,
        "precision": 8,
        "symbol": "USD"
      },
      "settling_asset": {
        "minimum_precision": 2,
        "precision": 8,
        "symbol": "USD"
      },
      "spot_index": {
        "symbol": ".DEXBTUSD"
      },
      "symbol": "P-BTC-68800-150226",
      "tick_size": "0.1",
      "underlying_asset": {
        "minimum_precision": 4,
        "precision": 8,
        "symbol": "BTC"
      }
    },
    "limit_price": "12",
    "bracket_trail_amount": null,
    "commission": "0",
    "bracket_order": null,
    "created_at": "2026-02-15T03:54:19.411146Z",
    "size": 800,
    "cancellation_reason": null,
    "bracket_stop_loss_price": null,
    "bracket_take_profit_price": null,
    "mmp": "disabled",
    "updated_at": "2026-02-15T03:56:08.787982Z",
    "paid_commission": "0.1739556",
    "bracket_stop_loss_limit_price": null
  },
  {
    "stop_order_type": null,
    "reduce_only": false,
    "average_fill_price": "45",
    "user_id": 21672861,
    "side": "sell",
    "trail_amount": null,
    "quote_size": null,
    "state": "open",
    "id": 1177619662,
    "stop_price": null,
    "margin_mode": "portfolio",
    "time_in_force": "gtc",
    "client_order_id": null,
    "meta_data": {
      "cashflow": "3.15",
      "ip": "2409:40e5:be:76c9:8000::",
      "otc": false,
      "pnl": "-0",
      "source": "mobile_app_android"
    },
    "product_id": 122099,
    "product_symbol": "P-BTC-68600-150226",
    "stop_trigger_method": null,
    "order_type": "limit_order",
    "unfilled_size": 430,
    "bracket_take_profit_limit_price": null,
    "product": {
      "contract_type": "put_options",
      "contract_unit_currency": "BTC",
      "contract_value": "0.001",
      "id": 122099,
      "notional_type": "vanilla",
      "quoting_asset": {
        "minimum_precision": 2,
        "precision": 8,
        "symbol": "USD"
      },
      "settling_asset": {
        "minimum_precision": 2,
        "precision": 8,
        "symbol": "USD"
      },
      "spot_index": {
        "symbol": ".DEXBTUSD"
      },
      "symbol": "P-BTC-68600-150226",
      "tick_size": "0.1",
      "underlying_asset": {
        "minimum_precision": 4,
        "precision": 8,
        "symbol": "BTC"
      }
    },
    "limit_price": "45",
    "bracket_trail_amount": null,
    "commission": "0",
    "bracket_order": null,
    "created_at": "2026-02-15T03:52:58.989792Z",
    "size": 500,
    "cancellation_reason": null,
    "bracket_stop_loss_price": null,
    "bracket_take_profit_price": null,
    "mmp": "disabled",
    "updated_at": "2026-02-15T03:53:03.248426Z",
    "paid_commission": "0.130095",
    "bracket_stop_loss_limit_price": null
  },
  {
    "stop_order_type": null,
    "reduce_only": false,
    "average_fill_price": "70",
    "user_id": 21672861,
    "side": "sell",
    "trail_amount": null,
    "quote_size": null,
    "state": "open",
    "id": 1177617600,
    "stop_price": null,
    "margin_mode": "portfolio",
    "time_in_force": "gtc",
    "client_order_id": null,
    "meta_data": {
      "cashflow": "1.61",
      "ip": "2409:40e5:be:76c9:8000::",
      "otc": false,
      "pnl": "-0",
      "source": "mobile_app_android",
      "user_updated_at": "2026-02-15T03:52:25.635Z"
    },
    "product_id": 122097,
    "product_symbol": "P-BTC-69000-150226",
    "stop_trigger_method": null,
    "order_type": "limit_order",
    "unfilled_size": 227,
    "bracket_take_profit_limit_price": null,
    "product": {
      "contract_type": "put_options",
      "contract_unit_currency": "BTC",
      "contract_value": "0.001",
      "id": 122097,
      "notional_type": "vanilla",
      "quoting_asset": {
        "minimum_precision": 2,
        "precision": 8,
        "symbol": "USD"
      },
      "settling_asset": {
        "minimum_precision": 2,
        "precision": 8,
        "symbol": "USD"
      },
      "spot_index": {
        "symbol": ".DEXBTUSD"
      },
      "symbol": "P-BTC-69000-150226",
      "tick_size": "0.1",
      "underlying_asset": {
        "minimum_precision": 4,
        "precision": 8,
        "symbol": "BTC"
      }
    },
    "limit_price": "50",
    "bracket_trail_amount": null,
    "commission": "0",
    "bracket_order": null,
    "created_at": "2026-02-15T03:51:27.049089Z",
    "size": 250,
    "cancellation_reason": null,
    "bracket_stop_loss_price": null,
    "bracket_take_profit_price": null,
    "mmp": "disabled",
    "updated_at": "2026-02-15T03:52:25.636535Z",
    "paid_commission": "0.066493",
    "bracket_stop_loss_limit_price": null
  },
  {
    "stop_order_type": null,
    "reduce_only": false,
    "average_fill_price": null,
    "user_id": 21672861,
    "side": "sell",
    "trail_amount": null,
    "quote_size": null,
    "state": "open",
    "id": 1177617355,
    "stop_price": null,
    "margin_mode": "portfolio",
    "time_in_force": "gtc",
    "client_order_id": null,
    "meta_data": {
      "ip": "2409:40e5:be:76c9:8000::",
      "otc": false,
      "source": "mobile_app_android",
      "user_updated_at": "2026-02-15T03:51:53.270Z"
    },
    "product_id": 122097,
    "product_symbol": "P-BTC-69000-150226",
    "stop_trigger_method": null,
    "order_type": "limit_order",
    "unfilled_size": 500,
    "bracket_take_profit_limit_price": null,
    "product": {
      "contract_type": "put_options",
      "contract_unit_currency": "BTC",
      "contract_value": "0.001",
      "id": 122097,
      "notional_type": "vanilla",
      "quoting_asset": {
        "minimum_precision": 2,
        "precision": 8,
        "symbol": "USD"
      },
      "settling_asset": {
        "minimum_precision": 2,
        "precision": 8,
        "symbol": "USD"
      },
      "spot_index": {
        "symbol": ".DEXBTUSD"
      },
      "symbol": "P-BTC-69000-150226",
      "tick_size": "0.1",
      "underlying_asset": {
        "minimum_precision": 4,
        "precision": 8,
        "symbol": "BTC"
      }
    },
    "limit_price": "60",
    "bracket_trail_amount": null,
    "commission": "0",
    "bracket_order": null,
    "created_at": "2026-02-15T03:51:17.014165Z",
    "size": 500,
    "cancellation_reason": null,
    "bracket_stop_loss_price": null,
    "bracket_take_profit_price": null,
    "mmp": "disabled",
    "updated_at": "2026-02-15T03:51:53.271312Z",
    "paid_commission": "0",
    "bracket_stop_loss_limit_price": null
  },
  {
    "stop_order_type": null,
    "reduce_only": false,
    "average_fill_price": null,
    "user_id": 21672861,
    "side": "buy",
    "trail_amount": null,
    "quote_size": null,
    "state": "open",
    "id": 1177611034,
    "stop_price": null,
    "margin_mode": "portfolio",
    "time_in_force": "gtc",
    "client_order_id": null,
    "meta_data": {
      "ip": "2409:40e5:be:76c9:8000::",
      "otc": false,
      "source": "mobile_app_android",
      "user_updated_at": "2026-02-15T03:48:13.570Z"
    },
    "product_id": 122137,
    "product_symbol": "P-BTC-69200-150226",
    "stop_trigger_method": null,
    "order_type": "limit_order",
    "unfilled_size": 150,
    "bracket_take_profit_limit_price": null,
    "product": {
      "contract_type": "put_options",
      "contract_unit_currency": "BTC",
      "contract_value": "0.001",
      "id": 122137,
      "notional_type": "vanilla",
      "quoting_asset": {
        "minimum_precision": 2,
        "precision": 8,
        "symbol": "USD"
      },
      "settling_asset": {
        "minimum_precision": 2,
        "precision": 8,
        "symbol": "USD"
      },
      "spot_index": {
        "symbol": ".DEXBTUSD"
      },
      "symbol": "P-BTC-69200-150226",
      "tick_size": "0.1",
      "underlying_asset": {
        "minimum_precision": 4,
        "precision": 8,
        "symbol": "BTC"
      }
    },
    "limit_price": "23",
    "bracket_trail_amount": null,
    "commission": "0",
    "bracket_order": null,
    "created_at": "2026-02-15T03:47:50.757578Z",
    "size": 150,
    "cancellation_reason": null,
    "bracket_stop_loss_price": null,
    "bracket_take_profit_price": null,
    "mmp": "disabled",
    "updated_at": "2026-02-15T03:48:13.570937Z",
    "paid_commission": "0",
    "bracket_stop_loss_limit_price": null
  },
  {
    "stop_order_type": null,
    "reduce_only": false,
    "average_fill_price": null,
    "user_id": 21672861,
    "side": "sell",
    "trail_amount": null,
    "quote_size": null,
    "state": "open",
    "id": 1177605687,
    "stop_price": null,
    "margin_mode": "portfolio",
    "time_in_force": "gtc",
    "client_order_id": null,
    "meta_data": {
      "ip": "2409:40e5:be:76c9:8000::",
      "otc": false,
      "source": "mobile_app_android",
      "user_updated_at": "2026-02-15T03:49:37.584Z"
    },
    "product_id": 122097,
    "product_symbol": "P-BTC-69000-150226",
    "stop_trigger_method": null,
    "order_type": "limit_order",
    "unfilled_size": 500,
    "bracket_take_profit_limit_price": null,
    "product": {
      "contract_type": "put_options",
      "contract_unit_currency": "BTC",
      "contract_value": "0.001",
      "id": 122097,
      "notional_type": "vanilla",
      "quoting_asset": {
        "minimum_precision": 2,
        "precision": 8,
        "symbol": "USD"
      },
      "settling_asset": {
        "minimum_precision": 2,
        "precision": 8,
        "symbol": "USD"
      },
      "spot_index": {
        "symbol": ".DEXBTUSD"
      },
      "symbol": "P-BTC-69000-150226",
      "tick_size": "0.1",
      "underlying_asset": {
        "minimum_precision": 4,
        "precision": 8,
        "symbol": "BTC"
      }
    },
    "limit_price": "100",
    "bracket_trail_amount": null,
    "commission": "0",
    "bracket_order": null,
    "created_at": "2026-02-15T03:45:44.666427Z",
    "size": 500,
    "cancellation_reason": null,
    "bracket_stop_loss_price": null,
    "bracket_take_profit_price": null,
    "mmp": "disabled",
    "updated_at": "2026-02-15T03:49:37.584633Z",
    "paid_commission": "0",
    "bracket_stop_loss_limit_price": null
  },
  {
    "stop_order_type": null,
    "reduce_only": false,
    "average_fill_price": null,
    "user_id": 21672861,
    "side": "sell",
    "trail_amount": null,
    "quote_size": null,
    "state": "open",
    "id": 1176928155,
    "stop_price": null,
    "margin_mode": "portfolio",
    "time_in_force": "gtc",
    "client_order_id": null,
    "meta_data": {
      "ip": "2409:40e4:8:f6eb:8000::",
      "otc": false,
      "source": "mobile_app_android",
      "user_updated_at": "2026-02-15T00:49:55.567Z"
    },
    "product_id": 122122,
    "product_symbol": "P-ETH-1980-150226",
    "stop_trigger_method": null,
    "order_type": "limit_order",
    "unfilled_size": 1000,
    "bracket_take_profit_limit_price": null,
    "product": {
      "contract_type": "put_options",
      "contract_unit_currency": "ETH",
      "contract_value": "0.01",
      "id": 122122,
      "notional_type": "vanilla",
      "quoting_asset": {
        "minimum_precision": 2,
        "precision": 8,
        "symbol": "USD"
      },
      "settling_asset": {
        "minimum_precision": 2,
        "precision": 8,
        "symbol": "USD"
      },
      "spot_index": {
        "symbol": ".DEETHUSD"
      },
      "symbol": "P-ETH-1980-150226",
      "tick_size": "0.01",
      "underlying_asset": {
        "minimum_precision": 4,
        "precision": 18,
        "symbol": "ETH"
      }
    },
    "limit_price": "4.9",
    "bracket_trail_amount": null,
    "commission": "0",
    "bracket_order": null,
    "created_at": "2026-02-14T14:12:17.065742Z",
    "size": 1000,
    "cancellation_reason": null,
    "bracket_stop_loss_price": null,
    "bracket_take_profit_price": null,
    "mmp": "disabled",
    "updated_at": "2026-02-15T00:49:55.567749Z",
    "paid_commission": "0",
    "bracket_stop_loss_limit_price": null
  }
]