[
  {
    "unfilled_size": 111,
    "close_on_trigger": "false",
    "stop_price": null,
    "stop_order_type": null,
    "state": "open",
    "client_order_id": null,
    "stop_trigger_method": null,
    "meta_data": {
      "ip": "2409:40e4:100a:5186:8000::",
      "otc": false,
      "source": "mobile_app_android",
      "user_updated_at": "2025-10-17T15:38:07.925Z"
    },
    "id": 996301932,
    "trail_amount": null,
    "product_symbol": "P-ETH-4850-311025",
    "bracket_trail_amount": null,
    "bracket_take_profit_limit_price": null,
    "user_id": 21672861,
    "bracket_stop_loss_price": null,
    "cancellation_reason": null,
    "updated_at": "2025-10-17T15:38:07.925560Z",
    "bracket_stop_loss_limit_price": null,
    "limit_price": "1115.99",
    "mmp": "disabled",
    "created_at": "2025-10-17T13:06:57.007384Z",
    "quote_size": null,
    "bracket_order": null,
    "bracket_take_profit_price": null,
    "reduce_only": true,
    "size": 111,
    "paid_commission": "0",
    "product_id": 98721,
    "product": {
      "contract_type": "put_options",
      "contract_unit_currency": "ETH",
      "contract_value": "0.01",
      "id": 98721,
      "notional_type": "vanilla",
      "quoting_asset": {
        "minimum_precision": 2,
        "precision": 8,
        "symbol": "USD"
      },
      "settling_asset": {
        "minimum_precision": 2,
        "precision": 8,
        "symbol": "USD"
      },
      "spot_index": {
        "symbol": ".DEETHUSD"
      },
      "symbol": "P-ETH-4850-311025",
      "tick_size": "0.01",
      "underlying_asset": {
        "minimum_precision": 4,
        "precision": 18,
        "symbol": "ETH"
      }
    },
    "time_in_force": "gtc",
    "order_type": "limit_order",
    "side": "sell",
    "commission": "0",
    "average_fill_price": null
  },
  {
    "unfilled_size": 1,
    "close_on_trigger": "false",
    "stop_price": null,
    "stop_order_type": null,
    "state": "open",
    "client_order_id": null,
    "stop_trigger_method": null,
    "meta_data": {
      "ip": "2409:40e4:100a:5186:8000::",
      "otc": false,
      "source": "mobile_app_android"
    },
    "id": 996238349,
    "trail_amount": null,
    "product_symbol": "P-ETH-4850-311025",
    "bracket_trail_amount": null,
    "bracket_take_profit_limit_price": null,
    "user_id": 21672861,
    "bracket_stop_loss_price": null,
    "cancellation_reason": null,
    "updated_at": "2025-10-17T12:08:31.309685Z",
    "bracket_stop_loss_limit_price": null,
    "limit_price": "600",
    "mmp": "disabled",
    "created_at": "2025-10-17T12:08:31.309685Z",
    "quote_size": null,
    "bracket_order": null,
    "bracket_take_profit_price": null,
    "reduce_only": false,
    "size": 1,
    "paid_commission": "0",
    "product_id": 98721,
    "product": {
      "contract_type": "put_options",
      "contract_unit_currency": "ETH",
      "contract_value": "0.01",
      "id": 98721,
      "notional_type": "vanilla",
      "quoting_asset": {
        "minimum_precision": 2,
        "precision": 8,
        "symbol": "USD"
      },
      "settling_asset": {
        "minimum_precision": 2,
        "precision": 8,
        "symbol": "USD"
      },
      "spot_index": {
        "symbol": ".DEETHUSD"
      },
      "symbol": "P-ETH-4850-311025",
      "tick_size": "0.01",
      "underlying_asset": {
        "minimum_precision": 4,
        "precision": 18,
        "symbol": "ETH"
      }
    },
    "time_in_force": "gtc",
    "order_type": "limit_order",
    "side": "buy",
    "commission": "0",
    "average_fill_price": null
  },
  {
    "unfilled_size": 1,
    "close_on_trigger": "false",
    "stop_price": null,
    "stop_order_type": null,
    "state": "open",
    "client_order_id": null,
    "stop_trigger_method": null,
    "meta_data": {
      "ip": "2409:40e4:100a:5186:8000::",
      "otc": false,
      "source": "mobile_app_android"
    },
    "id": 996238164,
    "trail_amount": null,
    "product_symbol": "P-ETH-4850-311025",
    "bracket_trail_amount": null,
    "bracket_take_profit_limit_price": null,
    "user_id": 21672861,
    "bracket_stop_loss_price": null,
    "cancellation_reason": null,
    "updated_at": "2025-10-17T12:08:22.264125Z",
    "bracket_stop_loss_limit_price": null,
    "limit_price": "500",
    "mmp": "disabled",
    "created_at": "2025-10-17T12:08:22.264125Z",
    "quote_size": null,
    "bracket_order": null,
    "bracket_take_profit_price": null,
    "reduce_only": false,
    "size": 1,
    "paid_commission": "0",
    "product_id": 98721,
    "product": {
      "contract_type": "put_options",
      "contract_unit_currency": "ETH",
      "contract_value": "0.01",
      "id": 98721,
      "notional_type": "vanilla",
      "quoting_asset": {
        "minimum_precision": 2,
        "precision": 8,
        "symbol": "USD"
      },
      "settling_asset": {
        "minimum_precision": 2,
        "precision": 8,
        "symbol": "USD"
      },
      "spot_index": {
        "symbol": ".DEETHUSD"
      },
      "symbol": "P-ETH-4850-311025",
      "tick_size": "0.01",
      "underlying_asset": {
        "minimum_precision": 4,
        "precision": 18,
        "symbol": "ETH"
      }
    },
    "time_in_force": "gtc",
    "order_type": "limit_order",
    "side": "buy",
    "commission": "0",
    "average_fill_price": null
  },
  {
    "unfilled_size": 1,
    "close_on_trigger": "false",
    "stop_price": null,
    "stop_order_type": null,
    "state": "open",
    "client_order_id": null,
    "stop_trigger_method": null,
    "meta_data": {
      "ip": "2409:40e4:100a:5186:8000::",
      "otc": false,
      "source": "mobile_app_android"
    },
    "id": 996238066,
    "trail_amount": null,
    "product_symbol": "P-ETH-4850-311025",
    "bracket_trail_amount": null,
    "bracket_take_profit_limit_price": null,
    "user_id": 21672861,
    "bracket_stop_loss_price": null,
    "cancellation_reason": null,
    "updated_at": "2025-10-17T12:08:16.968585Z",
    "bracket_stop_loss_limit_price": null,
    "limit_price": "400",
    "mmp": "disabled",
    "created_at": "2025-10-17T12:08:16.968585Z",
    "quote_size": null,
    "bracket_order": null,
    "bracket_take_profit_price": null,
    "reduce_only": false,
    "size": 1,
    "paid_commission": "0",
    "product_id": 98721,
    "product": {
      "contract_type": "put_options",
      "contract_unit_currency": "ETH",
      "contract_value": "0.01",
      "id": 98721,
      "notional_type": "vanilla",
      "quoting_asset": {
        "minimum_precision": 2,
        "precision": 8,
        "symbol": "USD"
      },
      "settling_asset": {
        "minimum_precision": 2,
        "precision": 8,
        "symbol": "USD"
      },
      "spot_index": {
        "symbol": ".DEETHUSD"
      },
      "symbol": "P-ETH-4850-311025",
      "tick_size": "0.01",
      "underlying_asset": {
        "minimum_precision": 4,
        "precision": 18,
        "symbol": "ETH"
      }
    },
    "time_in_force": "gtc",
    "order_type": "limit_order",
    "side": "buy",
    "commission": "0",
    "average_fill_price": null
  },
  {
    "unfilled_size": 1,
    "close_on_trigger": "false",
    "stop_price": null,
    "stop_order_type": null,
    "state": "open",
    "client_order_id": null,
    "stop_trigger_method": null,
    "meta_data": {
      "ip": "2409:40e4:100a:5186:8000::",
      "otc": false,
      "source": "mobile_app_android"
    },
    "id": 996237918,
    "trail_amount": null,
    "product_symbol": "P-ETH-4850-311025",
    "bracket_trail_amount": null,
    "bracket_take_profit_limit_price": null,
    "user_id": 21672861,
    "bracket_stop_loss_price": null,
    "cancellation_reason": null,
    "updated_at": "2025-10-17T12:08:09.945905Z",
    "bracket_stop_loss_limit_price": null,
    "limit_price": "300",
    "mmp": "disabled",
    "created_at": "2025-10-17T12:08:09.945905Z",
    "quote_size": null,
    "bracket_order": null,
    "bracket_take_profit_price": null,
    "reduce_only": false,
    "size": 1,
    "paid_commission": "0",
    "product_id": 98721,
    "product": {
      "contract_type": "put_options",
      "contract_unit_currency": "ETH",
      "contract_value": "0.01",
      "id": 98721,
      "notional_type": "vanilla",
      "quoting_asset": {
        "minimum_precision": 2,
        "precision": 8,
        "symbol": "USD"
      },
      "settling_asset": {
        "minimum_precision": 2,
        "precision": 8,
        "symbol": "USD"
      },
      "spot_index": {
        "symbol": ".DEETHUSD"
      },
      "symbol": "P-ETH-4850-311025",
      "tick_size": "0.01",
      "underlying_asset": {
        "minimum_precision": 4,
        "precision": 18,
        "symbol": "ETH"
      }
    },
    "time_in_force": "gtc",
    "order_type": "limit_order",
    "side": "buy",
    "commission": "0",
    "average_fill_price": null
  },
  {
    "unfilled_size": 1,
    "close_on_trigger": "false",
    "stop_price": null,
    "stop_order_type": null,
    "state": "open",
    "client_order_id": null,
    "stop_trigger_method": null,
    "meta_data": {
      "ip": "2409:40e4:100a:5186:8000::",
      "otc": false,
      "source": "mobile_app_android"
    },
    "id": 996237733,
    "trail_amount": null,
    "product_symbol": "P-ETH-4850-311025",
    "bracket_trail_amount": null,
    "bracket_take_profit_limit_price": null,
    "user_id": 21672861,
    "bracket_stop_loss_price": null,
    "cancellation_reason": null,
    "updated_at": "2025-10-17T12:08:01.615693Z",
    "bracket_stop_loss_limit_price": null,
    "limit_price": "200",
    "mmp": "disabled",
    "created_at": "2025-10-17T12:08:01.615693Z",
    "quote_size": null,
    "bracket_order": null,
    "bracket_take_profit_price": null,
    "reduce_only": false,
    "size": 1,
    "paid_commission": "0",
    "product_id": 98721,
    "product": {
      "contract_type": "put_options",
      "contract_unit_currency": "ETH",
      "contract_value": "0.01",
      "id": 98721,
      "notional_type": "vanilla",
      "quoting_asset": {
        "minimum_precision": 2,
        "precision": 8,
        "symbol": "USD"
      },
      "settling_asset": {
        "minimum_precision": 2,
        "precision": 8,
        "symbol": "USD"
      },
      "spot_index": {
        "symbol": ".DEETHUSD"
      },
      "symbol": "P-ETH-4850-311025",
      "tick_size": "0.01",
      "underlying_asset": {
        "minimum_precision": 4,
        "precision": 18,
        "symbol": "ETH"
      }
    },
    "time_in_force": "gtc",
    "order_type": "limit_order",
    "side": "buy",
    "commission": "0",
    "average_fill_price": null
  },
  {
    "unfilled_size": 1,
    "close_on_trigger": "false",
    "stop_price": null,
    "stop_order_type": null,
    "state": "open",
    "client_order_id": null,
    "stop_trigger_method": null,
    "meta_data": {
      "ip": "2409:40e4:100a:5186:8000::",
      "otc": false,
      "source": "mobile_app_android"
    },
    "id": 996237536,
    "trail_amount": null,
    "product_symbol": "P-ETH-4850-311025",
    "bracket_trail_amount": null,
    "bracket_take_profit_limit_price": null,
    "user_id": 21672861,
    "bracket_stop_loss_price": null,
    "cancellation_reason": null,
    "updated_at": "2025-10-17T12:07:54.342155Z",
    "bracket_stop_loss_limit_price": null,
    "limit_price": "100",
    "mmp": "disabled",
    "created_at": "2025-10-17T12:07:54.342155Z",
    "quote_size": null,
    "bracket_order": null,
    "bracket_take_profit_price": null,
    "reduce_only": false,
    "size": 1,
    "paid_commission": "0",
    "product_id": 98721,
    "product": {
      "contract_type": "put_options",
      "contract_unit_currency": "ETH",
      "contract_value": "0.01",
      "id": 98721,
      "notional_type": "vanilla",
      "quoting_asset": {
        "minimum_precision": 2,
        "precision": 8,
        "symbol": "USD"
      },
      "settling_asset": {
        "minimum_precision": 2,
        "precision": 8,
        "symbol": "USD"
      },
      "spot_index": {
        "symbol": ".DEETHUSD"
      },
      "symbol": "P-ETH-4850-311025",
      "tick_size": "0.01",
      "underlying_asset": {
        "minimum_precision": 4,
        "precision": 18,
        "symbol": "ETH"
      }
    },
    "time_in_force": "gtc",
    "order_type": "limit_order",
    "side": "buy",
    "commission": "0",
    "average_fill_price": null
  }
]