[
  {
    "order_type": "limit_order",
    "product_id": 127721,
    "user_id": 21672861,
    "updated_at": "2026-03-24T09:40:24.548994Z",
    "bracket_take_profit_limit_price": null,
    "quote_size": null,
    "bracket_trail_amount": null,
    "stop_price": null,
    "product_symbol": "P-BTC-71000-240326",
    "unfilled_size": 11,
    "bracket_stop_loss_limit_price": null,
    "state": "open",
    "id": 1241038847,
    "average_fill_price": null,
    "trail_amount": null,
    "limit_price": "120",
    "bracket_stop_loss_price": null,
    "stop_trigger_method": null,
    "margin_mode": "portfolio",
    "commission": "0",
    "product": {
      "contract_type": "put_options",
      "contract_unit_currency": "BTC",
      "contract_value": "0.001",
      "id": 127721,
      "notional_type": "vanilla",
      "quoting_asset": {
        "minimum_precision": 2,
        "precision": 8,
        "symbol": "USD"
      },
      "settling_asset": {
        "minimum_precision": 2,
        "precision": 8,
        "symbol": "USD"
      },
      "spot_index": {
        "symbol": ".DEXBTUSD"
      },
      "symbol": "P-BTC-71000-240326",
      "tick_size": "0.1",
      "underlying_asset": {
        "minimum_precision": 4,
        "precision": 8,
        "symbol": "BTC"
      }
    },
    "reduce_only": true,
    "created_at": "2026-03-24T09:40:24.380381Z",
    "stop_order_type": null,
    "mmp": "disabled",
    "bracket_take_profit_price": null,
    "side": "buy",
    "size": 11,
    "meta_data": {
      "otc": false,
      "user_updated_at": "2026-03-24T09:40:24.548Z"
    },
    "time_in_force": "gtc",
    "paid_commission": "0",
    "client_order_id": null,
    "bracket_order": null,
    "cancellation_reason": null
  },
  {
    "order_type": "limit_order",
    "product_id": 127726,
    "user_id": 21672861,
    "updated_at": "2026-03-24T09:39:58.891196Z",
    "bracket_take_profit_limit_price": null,
    "quote_size": null,
    "bracket_trail_amount": null,
    "stop_price": null,
    "product_symbol": "P-BTC-70000-240326",
    "unfilled_size": 1219,
    "bracket_stop_loss_limit_price": null,
    "state": "open",
    "id": 1241037967,
    "average_fill_price": null,
    "trail_amount": null,
    "limit_price": "16",
    "bracket_stop_loss_price": null,
    "stop_trigger_method": null,
    "margin_mode": "portfolio",
    "commission": "0",
    "product": {
      "contract_type": "put_options",
      "contract_unit_currency": "BTC",
      "contract_value": "0.001",
      "id": 127726,
      "notional_type": "vanilla",
      "quoting_asset": {
        "minimum_precision": 2,
        "precision": 8,
        "symbol": "USD"
      },
      "settling_asset": {
        "minimum_precision": 2,
        "precision": 8,
        "symbol": "USD"
      },
      "spot_index": {
        "symbol": ".DEXBTUSD"
      },
      "symbol": "P-BTC-70000-240326",
      "tick_size": "0.1",
      "underlying_asset": {
        "minimum_precision": 4,
        "precision": 8,
        "symbol": "BTC"
      }
    },
    "reduce_only": true,
    "created_at": "2026-03-24T09:39:58.891196Z",
    "stop_order_type": null,
    "mmp": "disabled",
    "bracket_take_profit_price": null,
    "side": "buy",
    "size": 1219,
    "meta_data": {
      "ip": "2409:40e5:9f:31b0:8000::",
      "otc": false,
      "source": "mobile_app_android"
    },
    "time_in_force": "gtc",
    "paid_commission": "0",
    "client_order_id": null,
    "bracket_order": null,
    "cancellation_reason": null
  },
  {
    "order_type": "limit_order",
    "product_id": 127721,
    "user_id": 21672861,
    "updated_at": "2026-03-24T09:40:02.371503Z",
    "bracket_take_profit_limit_price": null,
    "quote_size": null,
    "bracket_trail_amount": null,
    "stop_price": null,
    "product_symbol": "P-BTC-71000-240326",
    "unfilled_size": 83,
    "bracket_stop_loss_limit_price": null,
    "state": "open",
    "id": 1241036503,
    "average_fill_price": "135.032679738562091503",
    "trail_amount": null,
    "limit_price": "135",
    "bracket_stop_loss_price": null,
    "stop_trigger_method": null,
    "margin_mode": "portfolio",
    "commission": "0",
    "product": {
      "contract_type": "put_options",
      "contract_unit_currency": "BTC",
      "contract_value": "0.001",
      "id": 127721,
      "notional_type": "vanilla",
      "quoting_asset": {
        "minimum_precision": 2,
        "precision": 8,
        "symbol": "USD"
      },
      "settling_asset": {
        "minimum_precision": 2,
        "precision": 8,
        "symbol": "USD"
      },
      "spot_index": {
        "symbol": ".DEXBTUSD"
      },
      "symbol": "P-BTC-71000-240326",
      "tick_size": "0.1",
      "underlying_asset": {
        "minimum_precision": 4,
        "precision": 8,
        "symbol": "BTC"
      }
    },
    "reduce_only": true,
    "created_at": "2026-03-24T09:38:28.572953Z",
    "stop_order_type": null,
    "mmp": "disabled",
    "bracket_take_profit_price": null,
    "side": "buy",
    "size": 389,
    "meta_data": {
      "avg_exit_price": "135.0326797385620915032679739",
      "cashflow": "-41.32",
      "entry_price": "258.4761904761904761904761905",
      "exit_price_with_size": [
        {
          "price": "135.00000000",
          "size": "-50"
        },
        {
          "price": "135.00000000",
          "size": "-1"
        },
        {
          "price": "135.00000000",
          "size": "-2"
        },
        {
          "price": "135.00000000",
          "size": "-252"
        },
        {
          "price": "145.00000000",
          "size": "-1"
        }
      ],
      "fills_pnl_with_margin": [
        {
          "margin": "-12.92380952380952380952380953",
          "pnl": "6.17380952"
        },
        {
          "margin": "-0.2584761904761904761904761905",
          "pnl": "0.12347619"
        },
        {
          "margin": "-0.5169523809523809523809523810",
          "pnl": "0.24695238"
        },
        {
          "margin": "-65.13600000000000000000000001",
          "pnl": "31.11600000"
        },
        {
          "margin": "-0.25900000000000000000000000",
          "pnl": "0.11400000"
        }
      ],
      "ip": "2409:40e5:9f:31b0:8000::",
      "otc": false,
      "pnl": "37.77423809",
      "roe": "-47.75852072121321220798095580",
      "source": "mobile_app_android",
      "user_updated_at": "2026-03-24T09:39:23.599Z"
    },
    "time_in_force": "gtc",
    "paid_commission": "1.706516",
    "client_order_id": null,
    "bracket_order": null,
    "cancellation_reason": null
  },
  {
    "order_type": "limit_order",
    "product_id": 127724,
    "user_id": 21672861,
    "updated_at": "2026-03-24T09:39:31.939165Z",
    "bracket_take_profit_limit_price": null,
    "quote_size": null,
    "bracket_trail_amount": null,
    "stop_price": null,
    "product_symbol": "P-BTC-70400-240326",
    "unfilled_size": 914,
    "bracket_stop_loss_limit_price": null,
    "state": "open",
    "id": 1240995699,
    "average_fill_price": "77",
    "trail_amount": null,
    "limit_price": "79",
    "bracket_stop_loss_price": null,
    "stop_trigger_method": null,
    "margin_mode": "portfolio",
    "commission": "0",
    "product": {
      "contract_type": "put_options",
      "contract_unit_currency": "BTC",
      "contract_value": "0.001",
      "id": 127724,
      "notional_type": "vanilla",
      "quoting_asset": {
        "minimum_precision": 2,
        "precision": 8,
        "symbol": "USD"
      },
      "settling_asset": {
        "minimum_precision": 2,
        "precision": 8,
        "symbol": "USD"
      },
      "spot_index": {
        "symbol": ".DEXBTUSD"
      },
      "symbol": "P-BTC-70400-240326",
      "tick_size": "0.1",
      "underlying_asset": {
        "minimum_precision": 4,
        "precision": 8,
        "symbol": "BTC"
      }
    },
    "reduce_only": false,
    "created_at": "2026-03-24T09:00:49.104513Z",
    "stop_order_type": null,
    "mmp": "disabled",
    "bracket_take_profit_price": null,
    "side": "sell",
    "size": 1600,
    "meta_data": {
      "cashflow": "52.822",
      "ip": "2409:40e5:9f:31b0:8000::",
      "order_source": "place_order",
      "otc": false,
      "pnl": "-0",
      "source": "mobile_app_android",
      "user_updated_at": "2026-03-24T09:39:31.938Z"
    },
    "time_in_force": "gtc",
    "paid_commission": "2.1815486",
    "client_order_id": null,
    "bracket_order": null,
    "cancellation_reason": null
  },
  {
    "order_type": "limit_order",
    "product_id": 127779,
    "user_id": 21672861,
    "updated_at": "2026-03-24T09:40:21.020600Z",
    "bracket_take_profit_limit_price": null,
    "quote_size": null,
    "bracket_trail_amount": null,
    "stop_price": null,
    "product_symbol": "C-BTC-71800-240326",
    "unfilled_size": 500,
    "bracket_stop_loss_limit_price": null,
    "state": "open",
    "id": 1240981202,
    "average_fill_price": null,
    "trail_amount": null,
    "limit_price": "82.9",
    "bracket_stop_loss_price": null,
    "stop_trigger_method": null,
    "margin_mode": "portfolio",
    "commission": "0",
    "product": {
      "contract_type": "call_options",
      "contract_unit_currency": "BTC",
      "contract_value": "0.001",
      "id": 127779,
      "notional_type": "vanilla",
      "quoting_asset": {
        "minimum_precision": 2,
        "precision": 8,
        "symbol": "USD"
      },
      "settling_asset": {
        "minimum_precision": 2,
        "precision": 8,
        "symbol": "USD"
      },
      "spot_index": {
        "symbol": ".DEXBTUSD"
      },
      "symbol": "C-BTC-71800-240326",
      "tick_size": "0.1",
      "underlying_asset": {
        "minimum_precision": 4,
        "precision": 8,
        "symbol": "BTC"
      }
    },
    "reduce_only": false,
    "created_at": "2026-03-24T08:46:38.004573Z",
    "stop_order_type": null,
    "mmp": "disabled",
    "bracket_take_profit_price": null,
    "side": "sell",
    "size": 500,
    "meta_data": {
      "ip": "2409:40e5:9f:31b0:8000::",
      "order_source": "place_order",
      "otc": false,
      "source": "mobile_app_android",
      "user_updated_at": "2026-03-24T09:40:21.020Z"
    },
    "time_in_force": "gtc",
    "paid_commission": "0",
    "client_order_id": null,
    "bracket_order": null,
    "cancellation_reason": null
  },
  {
    "order_type": "limit_order",
    "product_id": 127729,
    "user_id": 21672861,
    "updated_at": "2026-03-24T09:40:25.666473Z",
    "bracket_take_profit_limit_price": null,
    "quote_size": null,
    "bracket_trail_amount": null,
    "stop_price": null,
    "product_symbol": "C-BTC-71400-240326",
    "unfilled_size": 317,
    "bracket_stop_loss_limit_price": null,
    "state": "open",
    "id": 1240956856,
    "average_fill_price": "118.321630804077010193",
    "trail_amount": null,
    "limit_price": "143",
    "bracket_stop_loss_price": null,
    "stop_trigger_method": null,
    "margin_mode": "portfolio",
    "commission": "0",
    "product": {
      "contract_type": "call_options",
      "contract_unit_currency": "BTC",
      "contract_value": "0.001",
      "id": 127729,
      "notional_type": "vanilla",
      "quoting_asset": {
        "minimum_precision": 2,
        "precision": 8,
        "symbol": "USD"
      },
      "settling_asset": {
        "minimum_precision": 2,
        "precision": 8,
        "symbol": "USD"
      },
      "spot_index": {
        "symbol": ".DEXBTUSD"
      },
      "symbol": "C-BTC-71400-240326",
      "tick_size": "0.1",
      "underlying_asset": {
        "minimum_precision": 4,
        "precision": 8,
        "symbol": "BTC"
      }
    },
    "reduce_only": false,
    "created_at": "2026-03-24T08:26:03.363823Z",
    "stop_order_type": null,
    "mmp": "disabled",
    "bracket_take_profit_price": null,
    "side": "sell",
    "size": 1200,
    "meta_data": {
      "cashflow": "104.478",
      "ip": "2409:40e5:9f:31b0:8000::",
      "order_source": "place_order",
      "otc": false,
      "pnl": "-0",
      "source": "mobile_app_android",
      "user_updated_at": "2026-03-24T09:40:25.666Z"
    },
    "time_in_force": "gtc",
    "paid_commission": "4.3149414",
    "client_order_id": null,
    "bracket_order": null,
    "cancellation_reason": null
  },
  {
    "order_type": "limit_order",
    "product_id": 127721,
    "user_id": 21672861,
    "updated_at": "2026-03-24T09:40:20.358252Z",
    "bracket_take_profit_limit_price": null,
    "quote_size": null,
    "bracket_trail_amount": null,
    "stop_price": null,
    "product_symbol": "P-BTC-71000-240326",
    "unfilled_size": 1171,
    "bracket_stop_loss_limit_price": null,
    "state": "open",
    "id": 1240920198,
    "average_fill_price": "402.810497237569060773",
    "trail_amount": null,
    "limit_price": 200,
    "bracket_stop_loss_price": null,
    "stop_trigger_method": null,
    "margin_mode": "portfolio",
    "commission": "0",
    "product": {
      "contract_type": "put_options",
      "contract_unit_currency": "BTC",
      "contract_value": "0.001",
      "id": 127721,
      "notional_type": "vanilla",
      "quoting_asset": {
        "minimum_precision": 2,
        "precision": 8,
        "symbol": "USD"
      },
      "settling_asset": {
        "minimum_precision": 2,
        "precision": 8,
        "symbol": "USD"
      },
      "spot_index": {
        "symbol": ".DEXBTUSD"
      },
      "symbol": "P-BTC-71000-240326",
      "tick_size": "0.1",
      "underlying_asset": {
        "minimum_precision": 4,
        "precision": 8,
        "symbol": "BTC"
      }
    },
    "reduce_only": false,
    "created_at": "2026-03-24T08:02:14.595066Z",
    "stop_order_type": null,
    "mmp": "disabled",
    "bracket_take_profit_price": null,
    "side": "sell",
    "size": 2800,
    "meta_data": {
      "cashflow": "656.1783",
      "ip": "2409:40e5:9f:31b0:8000::",
      "order_source": "place_order",
      "otc": false,
      "pnl": "0",
      "source": "mobile_app_android",
      "user_updated_at": "2026-03-24T09:40:20.357Z"
    },
    "time_in_force": "gtc",
    "paid_commission": "13.65311002",
    "client_order_id": null,
    "bracket_order": null,
    "cancellation_reason": null
  },
  {
    "order_type": "limit_order",
    "product_id": 127727,
    "user_id": 21672861,
    "updated_at": "2026-03-24T07:44:48.152328Z",
    "bracket_take_profit_limit_price": null,
    "quote_size": null,
    "bracket_trail_amount": null,
    "stop_price": null,
    "product_symbol": "P-BTC-69800-240326",
    "unfilled_size": 1000,
    "bracket_stop_loss_limit_price": null,
    "state": "open",
    "id": 1240886188,
    "average_fill_price": null,
    "trail_amount": null,
    "limit_price": "264",
    "bracket_stop_loss_price": null,
    "stop_trigger_method": null,
    "margin_mode": "portfolio",
    "commission": "0",
    "product": {
      "contract_type": "put_options",
      "contract_unit_currency": "BTC",
      "contract_value": "0.001",
      "id": 127727,
      "notional_type": "vanilla",
      "quoting_asset": {
        "minimum_precision": 2,
        "precision": 8,
        "symbol": "USD"
      },
      "settling_asset": {
        "minimum_precision": 2,
        "precision": 8,
        "symbol": "USD"
      },
      "spot_index": {
        "symbol": ".DEXBTUSD"
      },
      "symbol": "P-BTC-69800-240326",
      "tick_size": "0.1",
      "underlying_asset": {
        "minimum_precision": 4,
        "precision": 8,
        "symbol": "BTC"
      }
    },
    "reduce_only": false,
    "created_at": "2026-03-24T07:40:29.849835Z",
    "stop_order_type": null,
    "mmp": "disabled",
    "bracket_take_profit_price": null,
    "side": "sell",
    "size": 1000,
    "meta_data": {
      "ip": "2409:40e5:9f:31b0:8000::",
      "order_source": "place_order",
      "otc": false,
      "source": "mobile_app_android",
      "user_updated_at": "2026-03-24T07:44:48.151Z"
    },
    "time_in_force": "gtc",
    "paid_commission": "0",
    "client_order_id": null,
    "bracket_order": null,
    "cancellation_reason": null
  },
  {
    "order_type": "limit_order",
    "product_id": 127726,
    "user_id": 21672861,
    "updated_at": "2026-03-24T08:07:39.832908Z",
    "bracket_take_profit_limit_price": null,
    "quote_size": null,
    "bracket_trail_amount": null,
    "stop_price": null,
    "product_symbol": "P-BTC-70000-240326",
    "unfilled_size": 1000,
    "bracket_stop_loss_limit_price": null,
    "state": "open",
    "id": 1240885811,
    "average_fill_price": null,
    "trail_amount": null,
    "limit_price": "210",
    "bracket_stop_loss_price": null,
    "stop_trigger_method": null,
    "margin_mode": "portfolio",
    "commission": "0",
    "product": {
      "contract_type": "put_options",
      "contract_unit_currency": "BTC",
      "contract_value": "0.001",
      "id": 127726,
      "notional_type": "vanilla",
      "quoting_asset": {
        "minimum_precision": 2,
        "precision": 8,
        "symbol": "USD"
      },
      "settling_asset": {
        "minimum_precision": 2,
        "precision": 8,
        "symbol": "USD"
      },
      "spot_index": {
        "symbol": ".DEXBTUSD"
      },
      "symbol": "P-BTC-70000-240326",
      "tick_size": "0.1",
      "underlying_asset": {
        "minimum_precision": 4,
        "precision": 8,
        "symbol": "BTC"
      }
    },
    "reduce_only": false,
    "created_at": "2026-03-24T07:40:06.462409Z",
    "stop_order_type": null,
    "mmp": "disabled",
    "bracket_take_profit_price": null,
    "side": "sell",
    "size": 1000,
    "meta_data": {
      "ip": "2409:40e5:9f:31b0:8000::",
      "order_source": "place_order",
      "otc": false,
      "source": "mobile_app_android",
      "user_updated_at": "2026-03-24T08:07:39.832Z"
    },
    "time_in_force": "gtc",
    "paid_commission": "0",
    "client_order_id": null,
    "bracket_order": null,
    "cancellation_reason": null
  },
  {
    "order_type": "limit_order",
    "product_id": 127728,
    "user_id": 21672861,
    "updated_at": "2026-03-24T09:37:33.905287Z",
    "bracket_take_profit_limit_price": null,
    "quote_size": null,
    "bracket_trail_amount": null,
    "stop_price": null,
    "product_symbol": "C-BTC-71600-240326",
    "unfilled_size": 862,
    "bracket_stop_loss_limit_price": null,
    "state": "open",
    "id": 1240868455,
    "average_fill_price": "98.666666666666666667",
    "trail_amount": null,
    "limit_price": "99",
    "bracket_stop_loss_price": null,
    "stop_trigger_method": null,
    "margin_mode": "portfolio",
    "commission": "0",
    "product": {
      "contract_type": "call_options",
      "contract_unit_currency": "BTC",
      "contract_value": "0.001",
      "id": 127728,
      "notional_type": "vanilla",
      "quoting_asset": {
        "minimum_precision": 2,
        "precision": 8,
        "symbol": "USD"
      },
      "settling_asset": {
        "minimum_precision": 2,
        "precision": 8,
        "symbol": "USD"
      },
      "spot_index": {
        "symbol": ".DEXBTUSD"
      },
      "symbol": "C-BTC-71600-240326",
      "tick_size": "0.1",
      "underlying_asset": {
        "minimum_precision": 4,
        "precision": 8,
        "symbol": "BTC"
      }
    },
    "reduce_only": false,
    "created_at": "2026-03-24T07:26:57.906908Z",
    "stop_order_type": null,
    "mmp": "disabled",
    "bracket_take_profit_price": null,
    "side": "sell",
    "size": 1000,
    "meta_data": {
      "cashflow": "13.616",
      "ip": "2409:40e5:9f:31b0:8000::",
      "order_source": "place_order",
      "otc": false,
      "pnl": "-0",
      "source": "mobile_app_android",
      "user_updated_at": "2026-03-24T09:37:33.904Z"
    },
    "time_in_force": "gtc",
    "paid_commission": "0.5623408",
    "client_order_id": null,
    "bracket_order": null,
    "cancellation_reason": null
  },
  {
    "order_type": "limit_order",
    "product_id": 127730,
    "user_id": 21672861,
    "updated_at": "2026-03-24T09:40:18.630287Z",
    "bracket_take_profit_limit_price": null,
    "quote_size": null,
    "bracket_trail_amount": null,
    "stop_price": null,
    "product_symbol": "C-BTC-71200-240326",
    "unfilled_size": 1000,
    "bracket_stop_loss_limit_price": null,
    "state": "open",
    "id": 1240868053,
    "average_fill_price": null,
    "trail_amount": null,
    "limit_price": "249",
    "bracket_stop_loss_price": null,
    "stop_trigger_method": null,
    "margin_mode": "portfolio",
    "commission": "0",
    "product": {
      "contract_type": "call_options",
      "contract_unit_currency": "BTC",
      "contract_value": "0.001",
      "id": 127730,
      "notional_type": "vanilla",
      "quoting_asset": {
        "minimum_precision": 2,
        "precision": 8,
        "symbol": "USD"
      },
      "settling_asset": {
        "minimum_precision": 2,
        "precision": 8,
        "symbol": "USD"
      },
      "spot_index": {
        "symbol": ".DEXBTUSD"
      },
      "symbol": "C-BTC-71200-240326",
      "tick_size": "0.1",
      "underlying_asset": {
        "minimum_precision": 4,
        "precision": 8,
        "symbol": "BTC"
      }
    },
    "reduce_only": false,
    "created_at": "2026-03-24T07:26:41.675180Z",
    "stop_order_type": null,
    "mmp": "disabled",
    "bracket_take_profit_price": null,
    "side": "sell",
    "size": 1000,
    "meta_data": {
      "ip": "2409:40e5:9f:31b0:8000::",
      "order_source": "place_order",
      "otc": false,
      "source": "mobile_app_android",
      "user_updated_at": "2026-03-24T09:40:18.626Z"
    },
    "time_in_force": "gtc",
    "paid_commission": "0",
    "client_order_id": null,
    "bracket_order": null,
    "cancellation_reason": null
  },
  {
    "order_type": "limit_order",
    "product_id": 127731,
    "user_id": 21672861,
    "updated_at": "2026-03-24T09:40:14.739782Z",
    "bracket_take_profit_limit_price": null,
    "quote_size": null,
    "bracket_trail_amount": null,
    "stop_price": null,
    "product_symbol": "C-BTC-71000-240326",
    "unfilled_size": 1478,
    "bracket_stop_loss_limit_price": null,
    "state": "open",
    "id": 1240867104,
    "average_fill_price": "267",
    "trail_amount": null,
    "limit_price": "466",
    "bracket_stop_loss_price": null,
    "stop_trigger_method": null,
    "margin_mode": "portfolio",
    "commission": "0",
    "product": {
      "contract_type": "call_options",
      "contract_unit_currency": "BTC",
      "contract_value": "0.001",
      "id": 127731,
      "notional_type": "vanilla",
      "quoting_asset": {
        "minimum_precision": 2,
        "precision": 8,
        "symbol": "USD"
      },
      "settling_asset": {
        "minimum_precision": 2,
        "precision": 8,
        "symbol": "USD"
      },
      "spot_index": {
        "symbol": ".DEXBTUSD"
      },
      "symbol": "C-BTC-71000-240326",
      "tick_size": "0.1",
      "underlying_asset": {
        "minimum_precision": 4,
        "precision": 8,
        "symbol": "BTC"
      }
    },
    "reduce_only": false,
    "created_at": "2026-03-24T07:26:01.185277Z",
    "stop_order_type": null,
    "mmp": "disabled",
    "bracket_take_profit_price": null,
    "side": "sell",
    "size": 1500,
    "meta_data": {
      "cashflow": "5.874",
      "ip": "2409:40e5:9f:31b0:8000::",
      "order_source": "place_order",
      "otc": false,
      "pnl": "-0",
      "source": "mobile_app_android",
      "user_updated_at": "2026-03-24T09:40:14.739Z"
    },
    "time_in_force": "gtc",
    "paid_commission": "0.18413351",
    "client_order_id": null,
    "bracket_order": null,
    "cancellation_reason": null
  }
]